algorithms/__init__.py
algorithms/arrays/__init__.py
algorithms/arrays/add_to_array_form.py
algorithms/arrays/array_partition.py
algorithms/arrays/assign_cookies.py
algorithms/arrays/best_time_to_buy_stock.py
algorithms/arrays/best_time_to_buy_stock_II.py
algorithms/arrays/contains_duplicate_one.py
algorithms/arrays/contains_duplicate_range.py
algorithms/arrays/degree_array.py
algorithms/arrays/distribute_candies.py
algorithms/arrays/dynamic_array_implementation.py
algorithms/arrays/find_all_dissapeared_numbers.py
algorithms/arrays/find_all_duplicates.py
algorithms/arrays/find_pivot_index.py
algorithms/arrays/first_missing_positive.py
algorithms/arrays/friends_of_ages.py
algorithms/arrays/increasing_triplets.py
algorithms/arrays/intersection_two_arrays_II.py
algorithms/arrays/is_monotonic.py
algorithms/arrays/k_diff_pairs.py
algorithms/arrays/largest_number_twice_of_others.py
algorithms/arrays/longest_continuous_increasing_subsequence.py
algorithms/arrays/max_average_subarray.py
algorithms/arrays/max_consecutive_ones.py
algorithms/arrays/max_product_three_numbers.py
algorithms/arrays/maximize_distance_to_nearest_person.py
algorithms/arrays/maximum_subarray.py
algorithms/arrays/merge_intervals.py
algorithms/arrays/merge_sorted_array.py
algorithms/arrays/minimum_moves_to_equal_array.py
algorithms/arrays/move_zeroes.py
algorithms/arrays/next_greater_element.py
algorithms/arrays/non_decreasing_array.py
algorithms/arrays/number_plus_one.py
algorithms/arrays/partition_array_in_three.py
algorithms/arrays/place_flowers.py
algorithms/arrays/positions_large_groups.py
algorithms/arrays/product_of_array_except_self.py
algorithms/arrays/remove_duplicates_two.py
algorithms/arrays/rotate_array.py
algorithms/arrays/set_mismatch.py
algorithms/arrays/shortest_unsorted_subarray.py
algorithms/arrays/smallest_range_I.py
algorithms/arrays/sum_after_queries.py
algorithms/arrays/summary_ranges.py
algorithms/arrays/third_max_number.py
algorithms/arrays/two_sum_sorted_array.py
algorithms3-0.1.9.dist-info/LICENSE
algorithms3-0.1.9.dist-info/METADATA
algorithms3-0.1.9.dist-info/WHEEL
algorithms3-0.1.9.dist-info/top_level.txt
algorithms3-0.1.9.dist-info/RECORD
